maskmypy/__init__.py
maskmypy/analysis.py
maskmypy/atlas.py
maskmypy/tools.py
maskmypy/masks/__init__.py
maskmypy/masks/donut.py
maskmypy/masks/locationswap.py
maskmypy/masks/street.py
maskmypy/masks/voronoi.py
maskmypy-1.1.0.dist-info/licenses/LICENSE
tests/__init__.py
tests/conftest.py
tests/test_analysis.py
tests/test_atlas.py
tests/test_tools.py
maskmypy-1.1.0.dist-info/METADATA
maskmypy-1.1.0.dist-info/WHEEL
maskmypy-1.1.0.dist-info/top_level.txt
maskmypy-1.1.0.dist-info/RECORD
