Metadata-Version: 2.4
Name: maskmypy
Version: 1.1.0
Summary: Python tools for anonymizing geographic data.
Author: David Swanlund
Author-email: maskmypy@swanlund.dev
Classifier: Programming Language :: Python :: 3
Classifier: License :: OSI Approved :: MIT License
Classifier: Operating System :: OS Independent
Classifier: Topic :: Scientific/Engineering :: GIS
Requires-Python: >=3.10
License-File: LICENSE
Requires-Dist: osmnx<2.0,>=1.7.0
Requires-Dist: scikit-learn<2.0,>=1.1.1
Requires-Dist: pointpats<3.0,>=2.3.0
Provides-Extra: develop
Requires-Dist: pytest; extra == "develop"
Requires-Dist: black; extra == "develop"
Requires-Dist: mkdocs-material; extra == "develop"
Requires-Dist: mkdocs-roamlinks-plugin; extra == "develop"
Requires-Dist: mkdocs-git-revision-date-localized-plugin; extra == "develop"
Requires-Dist: mkdocstrings-python; extra == "develop"
Provides-Extra: extra
Requires-Dist: contextily>=1.2.0; extra == "extra"
Dynamic: author
Dynamic: author-email
Dynamic: classifier
Dynamic: description
Dynamic: description-content-type
Dynamic: license-file
Dynamic: provides-extra
Dynamic: requires-dist
Dynamic: requires-python
Dynamic: summary
